one2/__init__.py
one2/one2.py
one2-1.0.0.dist-info/LICENSE
one2-1.0.0.dist-info/METADATA
one2-1.0.0.dist-info/WHEEL
one2-1.0.0.dist-info/top_level.txt
one2-1.0.0.dist-info/RECORD
