Metadata-Version: 2.1
Name: one2
Version: 1.0.0
Summary: A module to print sequences from 1 to large ranges
Home-page: https://github.com/unknownmeovo/one2
Author: Hadi Raza
Author-email: hadiraza.9002@gmail.com
License: Apache License 2.0
Classifier: Programming Language :: Python :: 3
Classifier: License :: OSI Approved :: Apache Software License
Classifier: Operating System :: OS Independent
Requires-Python: >=3.6
License-File: LICENSE
